promptdev/__init__.py
promptdev/agents/__init__.py
promptdev/agents/providers.py
promptdev/agents/pydantic_agent.py
promptdev/cache/__init__.py
promptdev/cache/simple_cache.py
promptdev/cli.py
promptdev/config/__init__.py
promptdev/config/loader.py
promptdev/config/models.py
promptdev/evaluation/__init__.py
promptdev/evaluation/dataset.py
promptdev/evaluation/results.py
promptdev/evaluation/runner.py
promptdev/evaluators/__init__.py
promptdev/evaluators/pydantic_evaluators.py
promptdev-0.0.1.dist-info/WHEEL
promptdev-0.0.1.dist-info/entry_points.txt
promptdev-0.0.1.dist-info/METADATA
promptdev-0.0.1.dist-info/RECORD
