Metadata-Version: 2.3
Name: promptdev
Version: 0.0.1
Summary: Python-native prompt evaluation tool using PydanticAI
Classifier: Development Status :: 3 - Alpha
Classifier: Intended Audience :: Developers
Classifier: License :: OSI Approved :: MIT License
Classifier: Programming Language :: Python :: 3
Classifier: Programming Language :: Python :: 3.12
Classifier: Programming Language :: Python :: 3.13
Classifier: Topic :: Software Development :: Testing
Classifier: Topic :: Software Development :: Quality Assurance
Classifier: Topic :: Scientific/Engineering :: Artificial Intelligence
Classifier: Environment :: Console
Classifier: Operating System :: OS Independent
Requires-Dist: pydantic-ai==1.0.0b1
Requires-Dist: pydantic-evals
Requires-Dist: pydantic>=2.0.0
Requires-Dist: click>=8.0.0
Requires-Dist: pyyaml>=6.0.0
Requires-Dist: rich>=13.0.0
Requires-Dist: httpx>=0.27.0
Requires-Dist: jinja2>=3.0.0
Requires-Dist: pytest>=8.0.0 ; extra == 'dev'
Requires-Dist: pytest-asyncio>=0.21.0 ; extra == 'dev'
Requires-Dist: pytest-cov>=4.0.0 ; extra == 'dev'
Requires-Dist: ruff>=0.1.0 ; extra == 'dev'
Requires-Dist: safety>=3.0.0 ; extra == 'dev'
Requires-Dist: bandit[toml]>=1.7.0 ; extra == 'dev'
Requires-Dist: logfire>=0.1.0 ; extra == 'logfire'
Requires-Python: >=3.12
Provides-Extra: dev
Provides-Extra: logfire
